algebraical/__init__.py
algebraical/algebraical.py
algebraical-0.1.1.dist-info/LICENSE
algebraical-0.1.1.dist-info/METADATA
algebraical-0.1.1.dist-info/WHEEL
algebraical-0.1.1.dist-info/top_level.txt
algebraical-0.1.1.dist-info/RECORD
